Workbook

Sheet ASSUMPTION
A1: ASSUMPTION
A2: 1 | B2: I have to calculate Raw data through Excel function
A3: 2 | B3: I do not use any data through any website
A4: 3 | B4: I have to use Pivot table as well
A5: 4 | B5: I have to create Dashbord through Power bi

Sheet Raw Data
A1: XYZ COMPANY PVT. LTD.
A3: Date | B3: Department | C3: Expense Category | D3: Vendor | E3: Amount | F3: GST% | G3: GST Amount | H3: Total Expenses | I3: Cost Center
A4: =RANDBETWEEN(DATE(2023,1,1), DATE(2024,12,31)) -> 45063 | B4: =CHOOSE(RANDBETWEEN(1,8),"HR","Finance","Operations","IT","Marketing","Sales","Procurement","Admin") -> HR | C4: =CHOOSE(RANDBETWEEN(1,10),"Travel","Office Supplies","Salaries","Maintenance","Utilities","Software","Training","Marketing Spend","Transportation","Miscellaneous") -> Office Supplies | D4: =CHOOSE(RANDBETWEEN(1,10), "Infoserve Pvt Ltd", "Global Traders", "Alpha Logistics", "Bright Solutions", "Star Technologies", "Urban Office Mart", "QuickFix Services", "Skyline Marketing", "Rapid Transport", "Universal Systems") -> QuickFix Services | E4: =RANDBETWEEN(500,50000) -> 831 | F4: =CHOOSE(RANDBETWEEN(1,3),5,12,18) -> 18 | G4: =E4*F4/100 -> 149.58 | H4: =E4+G4 -> 980.58 | I4: =CHOOSE(RANDBETWEEN(1,6),"CC101","CC102","CC103","CC104","CC105","CC106") -> CC101
A5: =RANDBETWEEN(DATE(2023,1,1), DATE(2024,12,31)) -> 45625 | B5: =CHOOSE(RANDBETWEEN(1,8),"HR","Finance","Operations","IT","Marketing","Sales","Procurement","Admin") -> Operations | C5: =CHOOSE(RANDBETWEEN(1,10),"Travel","Office Supplies","Salaries","Maintenance","Utilities","Software","Training","Marketing Spend","Transportation","Miscellaneous") -> Software | D5: =CHOOSE(RANDBETWEEN(1,10), "Infoserve Pvt Ltd", "Global Traders", "Alpha Logistics", "Bright Solutions", "Star Technologies", "Urban Office Mart", "QuickFix Services", "Skyline Marketing", "Rapid Transport", "Universal Systems") -> Rapid Transport | E5: =RANDBETWEEN(500,50000) -> 27751 | F5: =CHOOSE(RANDBETWEEN(1,3),5,12,18) -> 5 | G5: =E5*F5/100 -> 1387.55 | H5: =E5+G5 -> 29138.55 | I5: =CHOOSE(RANDBETWEEN(1,6),"CC101","CC102","CC103","CC104","CC105","CC106") -> CC106
A6: =RANDBETWEEN(DATE(2023,1,1), DATE(2024,12,31)) -> 45049 | B6: =CHOOSE(RANDBETWEEN(1,8),"HR","Finance","Operations","IT","Marketing","Sales","Procurement","Admin") -> Sales | C6: =CHOOSE(RANDBETWEEN(1,10),"Travel","Office Supplies","Salaries","Maintenance","Utilities","Software","Training","Marketing Spend","Transportation","Miscellaneous") -> Training | D6: =CHOOSE(RANDBETWEEN(1,10), "Infoserve Pvt Ltd", "Global Traders", "Alpha Logistics", "Bright Solutions", "Star Technologies", "Urban Office Mart", "QuickFix Services", "Skyline Marketing", "Rapid Transport", "Universal Systems") -> Bright Solutions | E6: =RANDBETWEEN(500,50000) -> 27651 | F6: =CHOOSE(RANDBETWEEN(1,3),5,12,18) -> 12 | G6: =E6*F6/100 -> 3318.12 | H6: =E6+G6 -> 30969.12 | I6: =CHOOSE(RANDBETWEEN(1,6),"CC101","CC102","CC103","CC104","CC105","CC106") -> CC105
A7: =RANDBETWEEN(DATE(2023,1,1), DATE(2024,12,31)) -> 45525 | B7: =CHOOSE(RANDBETWEEN(1,8),"HR","Finance","Operations","IT","Marketing","Sales","Procurement","Admin") -> Finance | C7: =CHOOSE(RANDBETWEEN(1,10),"Travel","Office Supplies","Salaries","Maintenance","Utilities","Software","Training","Marketing Spend","Transportation","Miscellaneous") -> Miscellaneous | D7: =CHOOSE(RANDBETWEEN(1,10), "Infoserve Pvt Ltd", "Global Traders", "Alpha Logistics", "Bright Solutions", "Star Technologies", "Urban Office Mart", "QuickFix Services", "Skyline Marketing", "Rapid Transport", "Universal Systems") -> Alpha Logistics | E7: =RANDBETWEEN(500,50000) -> 10772 | F7: =CHOOSE(RANDBETWEEN(1,3),5,12,18) -> 18 | G7: =E7*F7/100 -> 1938.96 | H7: =E7+G7 -> 12710.96 | I7: =CHOOSE(RANDBETWEEN(1,6),"CC101","CC102","CC103","CC104","CC105","CC106") -> CC102
A8: =RANDBETWEEN(DATE(2023,1,1), DATE(2024,12,31)) -> 45520 | B8: =CHOOSE(RANDBETWEEN(1,8),"HR","Finance","Operations","IT","Marketing","Sales","Procurement","Admin") -> IT | C8: =CHOOSE(RANDBETWEEN(1,10),"Travel","Office Supplies","Salaries","Maintenance","Utilities","Software","Training","Marketing Spend","Transportation","Miscellaneous") -> Salaries | D8: =CHOOSE(RANDBETWEEN(1,10), "Infoserve Pvt Ltd", "Global Traders", "Alpha Logistics", "Bright Solutions", "Star Technologies", "Urban Office Mart", "QuickFix Services", "Skyline Marketing", "Rapid Transport", "Universal Systems") -> Alpha Logistics | E8: =RANDBETWEEN(500,50000) -> 14939 | F8: =CHOOSE(RANDBETWEEN(1,3),5,12,18) -> 5 | G8: =E8*F8/100 -> 746.95 | H8: =E8+G8 -> 15685.95 | I8: =CHOOSE(RANDBETWEEN(1,6),"CC101","CC102","CC103","CC104","CC105","CC106") -> CC104
A9: =RANDBETWEEN(DATE(2023,1,1), DATE(2024,12,31)) -> 45464 | B9: =CHOOSE(RANDBETWEEN(1,8),"HR","Finance","Operations","IT","Marketing","Sales","Procurement","Admin") -> Finance | C9: =CHOOSE(RANDBETWEEN(1,10),"Travel","Office Supplies","Salaries","Maintenance","Utilities","Software","Training","Marketing Spend","Transportation","Miscellaneous") -> Marketing Spend | D9: =CHOOSE(RANDBETWEEN(1,10), "Infoserve Pvt Ltd", "Global Traders", "Alpha Logistics", "Bright Solutions", "Star Technologies", "Urban Office Mart", "QuickFix Services", "Skyline Marketing", "Rapid Transport", "Universal Systems") -> Urban Office Mart | E9: =RANDBETWEEN(500,50000) -> 8109 | F9: =CHOOSE(RANDBETWEEN(1,3),5,12,18) -> 5 | G9: =E9*F9/100 -> 405.45 | H9: =E9+G9 -> 8514.45 | I9: =CHOOSE(RANDBETWEEN(1,6),"CC101","CC102","CC103","CC104","CC105","CC106") -> CC101
A10: =RANDBETWEEN(DATE(2023,1,1), DATE(2024,12,31)) -> 45464 | B10: =CHOOSE(RANDBETWEEN(1,8),"HR","Finance","Operations","IT","Marketing","Sales","Procurement","Admin") -> Sales | C10: =CHOOSE(RANDBETWEEN(1,10),"Travel","Office Supplies","Salaries","Maintenance","Utilities","Software","Training","Marketing Spend","Transportation","Miscellaneous") -> Transportation | D10: =CHOOSE(RANDBETWEEN(1,10), "Infoserve Pvt Ltd", "Global Traders", "Alpha Logistics", "Bright Solutions", "Star Technologies", "Urban Office Mart", "QuickFix Services", "Skyline Marketing", "Rapid Transport", "Universal Systems") -> Bright Solutions | E10: =RANDBETWEEN(500,50000) -> 14974 | F10: =CHOOSE(RANDBETWEEN(1,3),5,12,18) -> 18 | G10: =E10*F10/100 -> 2695.32 | H10: =E10+G10 -> 17669.32 | I10: =CHOOSE(RANDBETWEEN(1,6),"CC101","CC102","CC103","CC104","CC105","CC106") -> CC106
A11: =RANDBETWEEN(DATE(2023,1,1), DATE(2024,12,31)) -> 45132 | B11: =CHOOSE(RANDBETWEEN(1,8),"HR","Finance","Operations","IT","Marketing","Sales","Procurement","Admin") -> Sales | C11: =CHOOSE(RANDBETWEEN(1,10),"Travel","Office Supplies","Salaries","Maintenance","Utilities","Software","Training","Marketing Spend","Transportation","Miscellaneous") -> Software | D11: =CHOOSE(RANDBETWEEN(1,10), "Infoserve Pvt Ltd", "Global Traders", "Alpha Logistics", "Bright Solutions", "Star Technologies", "Urban Office Mart", "QuickFix Services", "Skyline Marketing", "Rapid Transport", "Universal Systems") -> Alpha Logistics | E11: =RANDBETWEEN(500,50000) -> 13986 | F11: =CHOOSE(RANDBETWEEN(1,3),5,12,18) -> 12 | G11: =E11*F11/100 -> 1678.32 | H11: =E11+G11 -> 15664.32 | I11: =CHOOSE(RANDBETWEEN(1,6),"CC101","CC102","CC103","CC104","CC105","CC106") -> CC106
A12: =RANDBETWEEN(DATE(2023,1,1), DATE(2024,12,31)) -> 45610 | B12: =CHOOSE(RANDBETWEEN(1,8),"HR","Finance","Operations","IT","Marketing","Sales","Procurement","Admin") -> Operations | C12: =CHOOSE(RANDBETWEEN(1,10),"Travel","Office Supplies","Salaries","Maintenance","Utilities","Software","Training","Marketing Spend","Transportation","Miscellaneous") -> Utilities | D12: =CHOOSE(RANDBETWEEN(1,10), "Infoserve Pvt Ltd", "Global Traders", "Alpha Logistics", "Bright Solutions", "Star Technologies", "Urban Office Mart", "QuickFix Services", "Skyline Marketing", "Rapid Transport", "Universal Systems") -> Global Traders | E12: =RANDBETWEEN(500,50000) -> 15365 | F12: =CHOOSE(RANDBETWEEN(1,3),5,12,18) -> 12 | G12: =E12*F12/100 -> 1843.8 | H12: =E12+G12 -> 17208.8 | I12: =CHOOSE(RANDBETWEEN(1,6),"CC101","CC102","CC103","CC104","CC105","CC106") -> CC101
A13: =RANDBETWEEN(DATE(2023,1,1), DATE(2024,12,31)) -> 45145 | B13: =CHOOSE(RANDBETWEEN(1,8),"HR","Finance","Operations","IT","Marketing","Sales","Procurement","Admin") -> Finance | C13: =CHOOSE(RANDBETWEEN(1,10),"Travel","Office Supplies","Salaries","Maintenance","Utilities","Software","Training","Marketing Spend","Transportation","Miscellaneous") -> Travel | D13: =CHOOSE(RANDBETWEEN(1,10), "Infoserve Pvt Ltd", "Global Traders", "Alpha Logistics", "Bright Solutions", "Star Technologies", "Urban Office Mart", "QuickFix Services", "Skyline Marketing", "Rapid Transport", "Universal Systems") -> Infoserve Pvt Ltd | E13: =RANDBETWEEN(500,50000) -> 30778 | F13: =CHOOSE(RANDBETWEEN(1,3),5,12,18) -> 12 | G13: =E13*F13/100 -> 3693.36 | H13: =E13+G13 -> 34471.36 | I13: =CHOOSE(RANDBETWEEN(1,6),"CC101","CC102","CC103","CC104","CC105","CC106") -> CC104
A14: =RANDBETWEEN(DATE(2023,1,1), DATE(2024,12,31)) -> 45173 | B14: =CHOOSE(RANDBETWEEN(1,8),"HR","Finance","Operations","IT","Marketing","Sales","Procurement","Admin") -> Operations | C14: =CHOOSE(RANDBETWEEN(1,10),"Travel","Office Supplies","Salaries","Maintenance","Utilities","Software","Training","Marketing Spend","Transportation","Miscellaneous") -> Utilities | D14: =CHOOSE(RANDBETWEEN(1,10), "Infoserve Pvt Ltd", "Global Traders", "Alpha Logistics", "Bright Solutions", "Star Technologies", "Urban Office Mart", "QuickFix Services", "Skyline Marketing", "Rapid Transport", "Universal Systems") -> Infoserve Pvt Ltd | E14: =RANDBETWEEN(500,50000) -> 49950 | F14: =CHOOSE(RANDBETWEEN(1,3),5,12,18) -> 18 | G14: =E14*F14/100 -> 8991 | H14: =E14+G14 -> 58941 | I14: =CHOOSE(RANDBETWEEN(1,6),"CC101","CC102","CC103","CC104","CC105","CC106") -> CC106
A15: =RANDBETWEEN(DATE(2023,1,1), DATE(2024,12,31)) -> 45107 | B15: =CHOOSE(RANDBETWEEN(1,8),"HR","Finance","Operations","IT","Marketing","Sales","Procurement","Admin") -> Operations | C15: =CHOOSE(RANDBETWEEN(1,10),"Travel","Office Supplies","Salaries","Maintenance","Utilities","Software","Training","Marketing Spend","Transportation","Miscellaneous") -> Travel | D15: =CHOOSE(RANDBETWEEN(1,10), "Infoserve Pvt Ltd", "Global Traders", "Alpha Logistics", "Bright Solutions", "Star Technologies", "Urban Office Mart", "QuickFix Services", "Skyline Marketing", "Rapid Transport", "Universal Systems") -> Skyline Marketing | E15: =RANDBETWEEN(500,50000) -> 41548 | F15: =CHOOSE(RANDBETWEEN(1,3),5,12,18) -> 5 | G15: =E15*F15/100 -> 2077.4 | H15: =E15+G15 -> 43625.4 | I15: =CHOOSE(RANDBETWEEN(1,6),"CC101","CC102","CC103","CC104","CC105","CC106") -> CC104
... A367: =RANDBETWEEN(DATE(2023,1,1), DATE(2024,12,31)) -> 45247 | B367: =CHOOSE(RANDBETWEEN(1,8),"HR","Finance","Operations","IT","Marketing","Sales","Procurement","Admin") -> Admin | C367: =CHOOSE(RANDBETWEEN(1,10),"Travel","Office Supplies","Salaries","Maintenance","Utilities","Software","Training","Marketing Spend","Transportation","Miscellaneous") -> Office Supplies | D367: =CHOOSE(RANDBETWEEN(1,10), "Infoserve Pvt Ltd", "Global Traders", "Alpha Logistics", "Bright Solutions", "Star Technologies", "Urban Office Mart", "QuickFix Services", "Skyline Marketing", "Rapid Transport", "Universal Systems") -> Urban Office Mart | E367: =RANDBETWEEN(500,50000) -> 15936 | F367: =CHOOSE(RANDBETWEEN(1,3),5,12,18) -> 12 | G367: =E367*F367/100 -> 1912.32 | H367: =E367+G367 -> 17848.32 | I367: =CHOOSE(RANDBETWEEN(1,6),"CC101","CC102","CC103","CC104","CC105","CC106") -> CC102

Sheet MIS SUMMARY
A1: MIS SUMMARY | L1: MIS SUMMARY
A3: MIS-1 | B3: Monthly Expenses trend | E3: MIS-3 | F3: Category wise Expenses
A5: Row Labels | B5: Sum of Total Expenses | E5: Sum of Total Expenses | F5: Column Labels
A6: 2023 | E6: Row Labels | F6: Admin | G6: Finance | H6: HR | I6: IT | J6: Marketing | K6: Operations | L6: Procurement | M6: Sales | N6: (blank) | O6: Grand Total
A7: Qtr1 | B7: 1215566.2 | E7: Maintenance | F7: 168933.05 | G7: 166134.85 | H7: 109218.52 | I7: 26906.88 | J7: 83041.02 | K7: 204177.88 | L7: 68054.06 | M7: 78646.74 | O7: 905113
A8: Qtr2 | B8: 1209246.8 | E8: Marketing Spend | F8: 70008.13 | G8: 127876.35 | H8: 72867.36 | I8: 85044.68 | J8: 228784.76 | K8: 104653.22 | L8: 112866.67 | M8: 21370.72 | O8: 823471.89
A9: Qtr3 | B9: 1210212.1 | E9: Miscellaneous | F9: 205497.02 | G9: 98222.34 | H9: 118664.73 | I9: 199711.04 | J9: 371198.62 | K9: 94040.29 | L9: 59178.77 | M9: 125302.59 | O9: 1271815.4
A10: Qtr4 | B10: 1009078.9 | E10: Office Supplies | F10: 270605.09 | G10: 264538.26 | H10: 128052 | I10: 228526.92 | J10: 118477.73 | K10: 63312.58 | L10: 132851.88 | M10: 69831.86 | O10: 1276196.3
A11: 2024 | E11: Salaries | F11: 116495.82 | G11: 36722.76 | H11: 269152.17 | I11: 62337.61 | J11: 86490.32 | K11: 100087.49 | L11: 80001.96 | M11: 164129.16 | O11: 915417.29
A12: Qtr1 | B12: 1123620.3 | E12: Software | F12: 142792.95 | G12: 133434.48 | H12: 179782.91 | I12: 99196.44 | J12: 57611.44 | K12: 66935.9 | L12: 71867.11 | M12: 85241.43 | O12: 836862.66
A13: Qtr2 | B13: 1625374.3 | E13: Training | F13: 164004.12 | G13: 141725.49 | H13: 139357.76 | I13: 48392.4 | J13: 132081.69 | K13: 47447.6 | L13: 87909.24 | M13: 48876.78 | O13: 809795.08
A14: Qtr3 | B14: 1374963.2 | E14: Transportation | F14: 221237.66 | G14: 74431.84 | H14: 446627.36 | I14: 25270.88 | J14: 236348.66 | K14: 116219.53 | L14: 195413.37 | M14: 70798.84 | O14: 1386348.1
A15: Qtr4 | B15: 1141081.7 | E15: Travel | F15: 135187.61 | G15: 48950.77 | H15: 226431.59 | I15: 126694.14 | J15: 81641.52 | K15: 104507.55 | L15: 103457.59 | M15: 85019.32 | O15: 911890.09
A16: Grand Total | B16: 9909143.5 | E16: Utilities | F16: 93694.85 | G16: 168749.64 | H16: 85761.8 | I16: 4551.68 | J16: 96521.67 | K16: 108198.9 | L16: 249046.81 | M16: 92342.82 | O16: 898868.17
E17: (blank)
E18: Grand Total | F18: 1588456.3 | G18: 1260786.8 | H18: 1775916.2 | I18: 906632.67 | J18: 1492197.4 | K18: 1009580.9 | L18: 1160647.5 | M18: 841560.26 | O18: 10035778
A19: MIS -2 | B19: Total Expenses by Department
A21: Row Labels | B21: Sum of Total Expenses | E21: MIS-4 | F21: GST paid Summary | I21: MIS-5 | J21: Vendor Wise Spend
A22: Admin | B22: 1588456.3 | E22: Row Labels | F22: Sum of GST Amount | I22: Row Labels | J22: Sum of Total Expenses
A23: Finance | B23: 1260786.8 | E23: 5 | F23: 144929.8 | I23: Alpha Logistics | J23: 1228145.6
A24: HR | B24: 1775916.2 | E24: 12 | F24: 398102.52 | I24: Bright Solutions | J24: 818632.6
A25: IT | B25: 906632.67 | E25: 18 | F25: 499824.72 | I25: Global Traders | J25: 937850.87
A26: Marketing | B26: 1492197.4 | E26: (blank) | I26: Infoserve Pvt Ltd | J26: 1167164.5
A27: Operations | B27: 1009580.9 | E27: Grand Total | F27: 1042857 | I27: QuickFix Services | J27: 854315.85
A28: Procurement | B28: 1160647.5 | I28: Rapid Transport | J28: 675497.95
A29: Sales | B29: 841560.26 | I29: Skyline Marketing | J29: 975697.46
A30: (blank) | I30: Star Technologies | J30: 1084537.7
A31: Grand Total | B31: 10035778 | I31: Universal Systems | J31: 1198533.6
I32: Urban Office Mart | J32: 1095401.8
I33: (blank)
I34: Grand Total | J34: 10035778

Sheet BUDGETING
A1: MONTH | B1: ACTUAL EXPENSES | C1: AVG SPEEND | D1: GROWTH % | E1: NEXT YEAR BUDGET
A2: 44927 | B2: =GETPIVOTDATA("Total Expenses",'PIVOT TABLE'!$A$4,"Months (Date)",1,"Years (Date)",2023) -> 190105.27 | C2: =GETPIVOTDATA("Total Expenses",'PIVOT TABLE'!$F$4,"Months (Date)",1,"Years (Date)",2023) -> 15842.106 | D2: =B3/B2-1 -> 0.85109124 | E2: =B2*(1+D2) -> 351902.2 | H2: # I have to use Actual Expenses and AVG speed in Pivot table which is mentioned in sheet
A3: 44958 | B3: =GETPIVOTDATA("Total Expenses",'PIVOT TABLE'!$A$4,"Months (Date)",2,"Years (Date)",2023) -> 351902.2 | C3: =GETPIVOTDATA("Total Expenses",'PIVOT TABLE'!$F$4,"Months (Date)",2,"Years (Date)",2023) -> 23460.147 | D3: =B4/B3-1 -> 0.38097645 | E3: =B3*(1+D3) -> 485968.65
A4: 44986 | B4: =GETPIVOTDATA("Total Expenses",'PIVOT TABLE'!$A$4,"Months (Date)",3,"Years (Date)",2023) -> 485968.65 | C4: =GETPIVOTDATA("Total Expenses",'PIVOT TABLE'!$F$4,"Months (Date)",3,"Years (Date)",2023) -> 32397.91 | D4: =B5/B4-1 -> -0.19855042 | E4: =B4*(1+D4) -> 389479.37
A5: 45017 | B5: =GETPIVOTDATA("Total Expenses",'PIVOT TABLE'!$A$4,"Months (Date)",4,"Years (Date)",2023) -> 389479.37 | C5: =GETPIVOTDATA("Total Expenses",'PIVOT TABLE'!$F$4,"Months (Date)",4,"Years (Date)",2023) -> 29959.952 | D5: =B6/B5-1 -> 0.022013027 | E5: =B5*(1+D5) -> 398052.99
A6: 45047 | B6: =GETPIVOTDATA("Total Expenses",'PIVOT TABLE'!$A$4,"Months (Date)",5,"Years (Date)",2023) -> 398052.99 | C6: =GETPIVOTDATA("Total Expenses",'PIVOT TABLE'!$F$4,"Months (Date)",5,"Years (Date)",2023) -> 28432.356 | D6: =B7/B6-1 -> 0.3958781 | E6: =B6*(1+D6) -> 555633.45
A7: 45078 | B7: =GETPIVOTDATA("Total Expenses",'PIVOT TABLE'!$A$4,"Months (Date)",6,"Years (Date)",2023) -> 555633.45 | C7: =GETPIVOTDATA("Total Expenses",'PIVOT TABLE'!$F$4,"Months (Date)",6,"Years (Date)",2023) -> 30868.525 | D7: =B8/B7-1 -> -0.14402531 | E7: =B7*(1+D7) -> 475608.17
A8: 45108 | B8: =GETPIVOTDATA("Total Expenses",'PIVOT TABLE'!$A$4,"Months (Date)",7,"Years (Date)",2023) -> 475608.17 | C8: =GETPIVOTDATA("Total Expenses",'PIVOT TABLE'!$F$4,"Months (Date)",7,"Years (Date)",2023) -> 27976.951 | D8: =B9/B8-1 -> 0.12607759 | E8: =B8*(1+D8) -> 535571.7
A9: 45139 | B9: =GETPIVOTDATA("Total Expenses",'PIVOT TABLE'!$A$4,"Months (Date)",8,"Years (Date)",2023) -> 535571.7 | C9: =GETPIVOTDATA("Total Expenses",'PIVOT TABLE'!$F$4,"Months (Date)",8,"Years (Date)",2023) -> 31504.218 | D9: =B10/B9-1 -> -0.36038069 | E9: =B9*(1+D9) -> 342562
A10: 45170 | B10: =GETPIVOTDATA("Total Expenses",'PIVOT TABLE'!$A$4,"Months (Date)",9,"Years (Date)",2023) -> 342562 | C10: =GETPIVOTDATA("Total Expenses",'PIVOT TABLE'!$F$4,"Months (Date)",9,"Years (Date)",2023) -> 31142 | D10: =B11/B10-1 -> 0.047769221 | E10: =B10*(1+D10) -> 358925.92
A11: 45200 | B11: =GETPIVOTDATA("Total Expenses",'PIVOT TABLE'!$A$4,"Months (Date)",10,"Years (Date)",2023) -> 358925.92 | C11: =GETPIVOTDATA("Total Expenses",'PIVOT TABLE'!$F$4,"Months (Date)",10,"Years (Date)",2023) -> 22432.87 | D11: =B12/B11-1 -> -0.36520046 | E11: =B11*(1+D11) -> 227846.01
A12: 45231 | B12: =GETPIVOTDATA("Total Expenses",'PIVOT TABLE'!$A$4,"Months (Date)",11,"Years (Date)",2023) -> 227846.01 | C12: =GETPIVOTDATA("Total Expenses",'PIVOT TABLE'!$F$4,"Months (Date)",11,"Years (Date)",2023) -> 28480.751 | D12: =B13/B12-1 -> 0.69649839 | E12: =B12*(1+D12) -> 386540.39
A13: 45261 | B13: =GETPIVOTDATA("Total Expenses",'PIVOT TABLE'!$A$4,"Months (Date)",12,"Years (Date)",2023) -> 386540.39 | C13: =GETPIVOTDATA("Total Expenses",'PIVOT TABLE'!$F$4,"Months (Date)",12,"Years (Date)",2023) -> 25769.359 | D13: =B14/B13-1 -> 0.038997891 | E13: =B13*(1+D13) -> 401614.65
A14: 45292 | B14: =GETPIVOTDATA("Total Expenses",'PIVOT TABLE'!$A$4,"Months (Date)",1,"Years (Date)",2024) -> 401614.65 | C14: =GETPIVOTDATA("Total Expenses",'PIVOT TABLE'!$F$4,"Months (Date)",1,"Years (Date)",2024) -> 30893.435 | D14: =B15/B14-1 -> 0.39709291 | E14: =B14*(1+D14) -> 561092.98
A15: 45323 | B15: =GETPIVOTDATA("Total Expenses",'PIVOT TABLE'!$A$4,"Months (Date)",2,"Years (Date)",2024) -> 561092.98 | C15: =GETPIVOTDATA("Total Expenses",'PIVOT TABLE'!$F$4,"Months (Date)",2,"Years (Date)",2024) -> 29531.209 | D15: =B16/B15-1 -> 0.081596797 | E15: =B15*(1+D15) -> 606876.37
A16: 45352 | B16: =GETPIVOTDATA("Total Expenses",'PIVOT TABLE'!$A$4,"Months (Date)",3,"Years (Date)",2024) -> 606876.37 | C16: =GETPIVOTDATA("Total Expenses",'PIVOT TABLE'!$F$4,"Months (Date)",3,"Years (Date)",2024) -> 22476.903 | D16: =B17/B16-1 -> -0.59275892 | E16: =B16*(1+D16) -> 247144.99
A17: 45383 | B17: =GETPIVOTDATA("Total Expenses",'PIVOT TABLE'!$A$4,"Months (Date)",4,"Years (Date)",2024) -> 247144.99 | C17: =GETPIVOTDATA("Total Expenses",'PIVOT TABLE'!$F$4,"Months (Date)",4,"Years (Date)",2024) -> 20595.416 | D17: =B18/B17-1 -> 1.0015586 | E17: =B17*(1+D17) -> 494675.19
A18: 45413 | B18: =GETPIVOTDATA("Total Expenses",'PIVOT TABLE'!$A$4,"Months (Date)",5,"Years (Date)",2024) -> 494675.19 | C18: =GETPIVOTDATA("Total Expenses",'PIVOT TABLE'!$F$4,"Months (Date)",5,"Years (Date)",2024) -> 27481.955 | D18: =B19/B18-1 -> -0.3443539 | E18: =B18*(1+D18) -> 324331.86
A19: 45444 | B19: =GETPIVOTDATA("Total Expenses",'PIVOT TABLE'!$A$4,"Months (Date)",6,"Years (Date)",2024) -> 324331.86 | C19: =GETPIVOTDATA("Total Expenses",'PIVOT TABLE'!$F$4,"Months (Date)",6,"Years (Date)",2024) -> 29484.715 | D19: =B20/B19-1 -> 0.01271605 | E19: =B19*(1+D19) -> 328456.08
A20: 45474 | B20: =GETPIVOTDATA("Total Expenses",'PIVOT TABLE'!$A$4,"Months (Date)",7,"Years (Date)",2024) -> 328456.08 | C20: =GETPIVOTDATA("Total Expenses",'PIVOT TABLE'!$F$4,"Months (Date)",7,"Years (Date)",2024) -> 27371.34 | D20: =B21/B20-1 -> 0.20059001 | E20: =B20*(1+D20) -> 394341.09
A21: 45505 | B21: =GETPIVOTDATA("Total Expenses",'PIVOT TABLE'!$A$4,"Months (Date)",8,"Years (Date)",2024) -> 394341.09 | C21: =GETPIVOTDATA("Total Expenses",'PIVOT TABLE'!$F$4,"Months (Date)",8,"Years (Date)",2024) -> 30333.93 | D21: =B22/B21-1 -> 0.069638216 | E21: =B21*(1+D21) -> 421802.3
A22: 45536 | B22: =GETPIVOTDATA("Total Expenses",'PIVOT TABLE'!$A$4,"Months (Date)",9,"Years (Date)",2024) -> 421802.3 | C22: =GETPIVOTDATA("Total Expenses",'PIVOT TABLE'!$F$4,"Months (Date)",9,"Years (Date)",2024) -> 28120.153 | D22: =B23/B22-1 -> 0.3524907 | E22: =B22*(1+D22) -> 570483.69
A23: 45566 | B23: =GETPIVOTDATA("Total Expenses",'PIVOT TABLE'!$A$4,"Months (Date)",10,"Years (Date)",2024) -> 570483.69 | C23: =GETPIVOTDATA("Total Expenses",'PIVOT TABLE'!$F$4,"Months (Date)",10,"Years (Date)",2024) -> 27165.89 | D23: =B24/B23-1 -> -0.24190699 | E23: =B23*(1+D23) -> 432479.7
A24: 45597 | B24: =GETPIVOTDATA("Total Expenses",'PIVOT TABLE'!$A$4,"Months (Date)",11,"Years (Date)",2024) -> 432479.7 | C24: =GETPIVOTDATA("Total Expenses",'PIVOT TABLE'!$F$4,"Months (Date)",11,"Years (Date)",2024) -> 30891.407 | D24: =B25/B24-1 -> 0.28163939 | E24: =B24*(1+D24) -> 554283.02
A25: 45627 | B25: =GETPIVOTDATA("Total Expenses",'PIVOT TABLE'!$A$4,"Months (Date)",12,"Years (Date)",2024) -> 554283.02 | C25: =GETPIVOTDATA("Total Expenses",'PIVOT TABLE'!$F$4,"Months (Date)",12,"Years (Date)",2024) -> 30793.501 | D25: =B26/B25-1 -> -1 | E25: =B25*(1+D25) -> 0

Sheet FORECASTING
A1: MONTH | B1: ACTUAL | C1: FORECAST GROWTH | E1: MONTH | F1: FORECAST GROWTH | G1: FORECAST MOVING AVG | H1: FORECAST ETS
A2: 44927 | B2: =GETPIVOTDATA("Total Expenses",'PIVOT TABLE'!$A$4,"Months (Date)",1,"Years (Date)",2023) -> 190105.27 | C2: =B3/B2-1 -> 0.85109124 | E2: 45658 | F2: =AVERAGE(C2:C25) -> 0.071226998 | G2: =AVERAGE(B2:B25) -> 418157.42 | H2: =_xlfn.FORECAST.ETS(E2,B2:B25,A2:A25) -> 342021.8
A3: 44958 | B3: =GETPIVOTDATA("Total Expenses",'PIVOT TABLE'!$A$4,"Months (Date)",2,"Years (Date)",2023) -> 351902.2 | C3: =B4/B3-1 -> 0.38097645
A4: 44986 | B4: =GETPIVOTDATA("Total Expenses",'PIVOT TABLE'!$A$4,"Months (Date)",3,"Years (Date)",2023) -> 485968.65 | C4: =B5/B4-1 -> -0.19855042
A5: 45017 | B5: =GETPIVOTDATA("Total Expenses",'PIVOT TABLE'!$A$4,"Months (Date)",4,"Years (Date)",2023) -> 389479.37 | C5: =B6/B5-1 -> 0.022013027
A6: 45047 | B6: =GETPIVOTDATA("Total Expenses",'PIVOT TABLE'!$A$4,"Months (Date)",5,"Years (Date)",2023) -> 398052.99 | C6: =B7/B6-1 -> 0.3958781
A7: 45078 | B7: =GETPIVOTDATA("Total Expenses",'PIVOT TABLE'!$A$4,"Months (Date)",6,"Years (Date)",2023) -> 555633.45 | C7: =B8/B7-1 -> -0.14402531
A8: 45108 | B8: =GETPIVOTDATA("Total Expenses",'PIVOT TABLE'!$A$4,"Months (Date)",7,"Years (Date)",2023) -> 475608.17 | C8: =B9/B8-1 -> 0.12607759
A9: 45139 | B9: =GETPIVOTDATA("Total Expenses",'PIVOT TABLE'!$A$4,"Months (Date)",8,"Years (Date)",2023) -> 535571.7 | C9: =B10/B9-1 -> -0.36038069
A10: 45170 | B10: =GETPIVOTDATA("Total Expenses",'PIVOT TABLE'!$A$4,"Months (Date)",9,"Years (Date)",2023) -> 342562 | C10: =B11/B10-1 -> 0.047769221
A11: 45200 | B11: =GETPIVOTDATA("Total Expenses",'PIVOT TABLE'!$A$4,"Months (Date)",10,"Years (Date)",2023) -> 358925.92 | C11: =B12/B11-1 -> -0.36520046
A12: 45231 | B12: =GETPIVOTDATA("Total Expenses",'PIVOT TABLE'!$A$4,"Months (Date)",11,"Years (Date)",2023) -> 227846.01 | C12: =B13/B12-1 -> 0.69649839
A13: 45261 | B13: =GETPIVOTDATA("Total Expenses",'PIVOT TABLE'!$A$4,"Months (Date)",12,"Years (Date)",2023) -> 386540.39 | C13: =B14/B13-1 -> 0.038997891
A14: 45292 | B14: =GETPIVOTDATA("Total Expenses",'PIVOT TABLE'!$A$4,"Months (Date)",1,"Years (Date)",2024) -> 401614.65 | C14: =B15/B14-1 -> 0.39709291
A15: 45323 | B15: =GETPIVOTDATA("Total Expenses",'PIVOT TABLE'!$A$4,"Months (Date)",2,"Years (Date)",2024) -> 561092.98 | C15: =B16/B15-1 -> 0.081596797
A16: 45352 | B16: =GETPIVOTDATA("Total Expenses",'PIVOT TABLE'!$A$4,"Months (Date)",3,"Years (Date)",2024) -> 606876.37 | C16: =B17/B16-1 -> -0.59275892
A17: 45383 | B17: =GETPIVOTDATA("Total Expenses",'PIVOT TABLE'!$A$4,"Months (Date)",4,"Years (Date)",2024) -> 247144.99 | C17: =B18/B17-1 -> 1.0015586
A18: 45413 | B18: =GETPIVOTDATA("Total Expenses",'PIVOT TABLE'!$A$4,"Months (Date)",5,"Years (Date)",2024) -> 494675.19 | C18: =B19/B18-1 -> -0.3443539
A19: 45444 | B19: =GETPIVOTDATA("Total Expenses",'PIVOT TABLE'!$A$4,"Months (Date)",6,"Years (Date)",2024) -> 324331.86 | C19: =B20/B19-1 -> 0.01271605
A20: 45474 | B20: =GETPIVOTDATA("Total Expenses",'PIVOT TABLE'!$A$4,"Months (Date)",7,"Years (Date)",2024) -> 328456.08 | C20: =B21/B20-1 -> 0.20059001
A21: 45505 | B21: =GETPIVOTDATA("Total Expenses",'PIVOT TABLE'!$A$4,"Months (Date)",8,"Years (Date)",2024) -> 394341.09 | C21: =B22/B21-1 -> 0.069638216
A22: 45536 | B22: =GETPIVOTDATA("Total Expenses",'PIVOT TABLE'!$A$4,"Months (Date)",9,"Years (Date)",2024) -> 421802.3 | C22: =B23/B22-1 -> 0.3524907
A23: 45566 | B23: =GETPIVOTDATA("Total Expenses",'PIVOT TABLE'!$A$4,"Months (Date)",10,"Years (Date)",2024) -> 570483.69 | C23: =B24/B23-1 -> -0.24190699
A24: 45597 | B24: =GETPIVOTDATA("Total Expenses",'PIVOT TABLE'!$A$4,"Months (Date)",11,"Years (Date)",2024) -> 432479.7 | C24: =B25/B24-1 -> 0.28163939
A25: 45627 | B25: =GETPIVOTDATA("Total Expenses",'PIVOT TABLE'!$A$4,"Months (Date)",12,"Years (Date)",2024) -> 554283.02 | C25: =B26/B25-1 -> -1

Sheet PIVOT TABLE
A4: Row Labels | B4: Sum of Total Expenses | F4: Row Labels | G4: Average of Total Expenses
A5: 2023 | F5: 2023
A6: Jan | B6: 190105.27 | F6: Jan | G6: 15842.106
A7: Feb | B7: 351902.2 | F7: Feb | G7: 23460.147
A8: Mar | B8: 485968.65 | F8: Mar | G8: 32397.91
A9: Apr | B9: 389479.37 | F9: Apr | G9: 29959.952
A10: May | B10: 398052.99 | F10: May | G10: 28432.356
A11: Jun | B11: 555633.45 | F11: Jun | G11: 30868.525
A12: Jul | B12: 475608.17 | F12: Jul | G12: 27976.951
A13: Aug | B13: 535571.7 | F13: Aug | G13: 31504.218
A14: Sep | B14: 342562 | F14: Sep | G14: 31142
A15: Oct | B15: 358925.92 | F15: Oct | G15: 22432.87
A16: Nov | B16: 227846.01 | F16: Nov | G16: 28480.751
A17: Dec | B17: 386540.39 | F17: Dec | G17: 25769.359
A18: 2024 | F18: 2024
A19: Jan | B19: 401614.65 | F19: Jan | G19: 30893.435
A20: Feb | B20: 561092.98 | F20: Feb | G20: 29531.209
A21: Mar | B21: 606876.37 | F21: Mar | G21: 22476.903
A22: Apr | B22: 247144.99 | F22: Apr | G22: 20595.416
A23: May | B23: 494675.19 | F23: May | G23: 27481.955
A24: Jun | B24: 324331.86 | F24: Jun | G24: 29484.715
A25: Jul | B25: 328456.08 | F25: Jul | G25: 27371.34
A26: Aug | B26: 394341.09 | F26: Aug | G26: 30333.93
A27: Sep | B27: 421802.3 | F27: Sep | G27: 28120.153
A28: Oct | B28: 570483.69 | F28: Oct | G28: 27165.89
A29: Nov | B29: 432479.7 | F29: Nov | G29: 30891.407
A30: Dec | B30: 554283.02 | F30: Dec | G30: 30793.501
A31: Grand Total | B31: 10035778 | F31: Grand Total | G31: 27570.819
