Workbook

Sheet Assumption
A2: 1 | B2: I have Change old Salesperson Name to Raw Name because it was error and Create new column which is Salesperson
A3: 2 | B3: I have changed old discount % to Raw Discount and Create new Discount column with Prform Some calculation.
A4: 3 | B4: Delete 2 rows which is duplicate in order id.

Sheet orders
A1: Order ID | B1: Order Date | C1: Customer Name | D1: Region | E1: Raw Name | F1: Salesperson Name | G1: Product | H1: Quantity | I1: Unit Price | J1: Raw Discount % | K1: Discount% | L1: Payment Status | M1: Net Revenue | N1: Revenue | O1: Month
A2: O001 | B2: 45770 | C2: Megha S | D2: South | E2: Neha Sharma | F2: =PROPER(E2) -> Neha Sharma | G2: Printer | H2: 2 | I2: 12000 | J2: 5 | K2: =IF(J2>1,J2/100,J2) -> 0.05 | L2: Paid | M2: =IF(L2="paid",H2*I2*(1-K2),0) -> 22800 | N2: =IF(L2="paid",H2*I2,0) -> 24000 | O2: =TEXT(B2,"mmm-yyy") -> Apr-2025
A3: O002 | B3: 45775 | C3: Naveen | D3: South | E3: RIYA GUPTA | F3: =PROPER(E3) -> Riya Gupta | G3: Office Chair | H3: 2 | I3: 7500 | J3: 6 | K3: =IF(J3>1,J3/100,J3) -> 0.06 | L3: Paid | M3: =IF(L3="paid",H3*I3*(1-K3),0) -> 14100 | N3: =IF(L3="paid",H3*I3,0) -> 15000 | O3: =TEXT(B3,"mmm-yyy") -> Apr-2025
A4: O003 | B4: 45723 | C4: Sahil | D4: North | E4: srikanth verma | F4: =PROPER(E4) -> Srikanth Verma | G4: Mobile | H4: 6 | I4: 18000 | J4: 8 | K4: =IF(J4>1,J4/100,J4) -> 0.08 | L4: Pending | M4: =IF(L4="paid",H4*I4*(1-K4),0) -> 0 | N4: =IF(L4="paid",H4*I4,0) -> 0 | O4: =TEXT(B4,"mmm-yyy") -> Mar-2025
A5: O004 | B5: 45702 | C5: Maya | D5: West | E5: Neha Sharma | F5: =PROPER(E5) -> Neha Sharma | G5: Mobile | H5: 6 | I5: 18000 | J5: 8 | K5: =IF(J5>1,J5/100,J5) -> 0.08 | L5: Pending | M5: =IF(L5="paid",H5*I5*(1-K5),0) -> 0 | N5: =IF(L5="paid",H5*I5,0) -> 0 | O5: =TEXT(B5,"mmm-yyy") -> Feb-2025
A6: O005 | B6: 45708 | C6: Ramesh K | D6: North | E6: Srikanth Verma | F6: =PROPER(E6) -> Srikanth Verma | G6: Laptop | H6: 1 | I6: 55000 | J6: 0.08 | K6: =IF(J6>1,J6/100,J6) -> 0.08 | L6: Pending | M6: =IF(L6="paid",H6*I6*(1-K6),0) -> 0 | N6: =IF(L6="paid",H6*I6,0) -> 0 | O6: =TEXT(B6,"mmm-yyy") -> Feb-2025
A7: O006 | B7: 45719 | C7: Arjun Reddy | D7: East | E7: Anita Joseph | F7: =PROPER(E7) -> Anita Joseph | G7: Laptop | H7: 2 | I7: 55000 | J7: 6 | K7: =IF(J7>1,J7/100,J7) -> 0.06 | L7: Paid | M7: =IF(L7="paid",H7*I7*(1-K7),0) -> 103400 | N7: =IF(L7="paid",H7*I7,0) -> 110000 | O7: =TEXT(B7,"mmm-yyy") -> Mar-2025
A8: O007 | B8: 45758 | C8: Priya | D8: West | E8: RAHUL NAIR | F8: =PROPER(E8) -> Rahul Nair | G8: Printer | H8: 3 | I8: 12000 | J8: 5 | K8: =IF(J8>1,J8/100,J8) -> 0.05 | L8: Paid | M8: =IF(L8="paid",H8*I8*(1-K8),0) -> 34200 | N8: =IF(L8="paid",H8*I8,0) -> 36000 | O8: =TEXT(B8,"mmm-yyy") -> Apr-2025
A9: O008 | B9: 45735 | C9: Deepa Menon | D9: South | E9: Neha Sharma | F9: =PROPER(E9) -> Neha Sharma | G9: Mobile | H9: 4 | I9: 18000 | J9: 7 | K9: =IF(J9>1,J9/100,J9) -> 0.07 | L9: Paid | M9: =IF(L9="paid",H9*I9*(1-K9),0) -> 66960 | N9: =IF(L9="paid",H9*I9,0) -> 72000 | O9: =TEXT(B9,"mmm-yyy") -> Mar-2025
A10: O009 | B10: 45713 | C10: Manju S | D10: East | E10: =E75 -> neha sharma | F10: =F75 -> Neha Sharma | G10: Laptop | H10: 3 | I10: 55000 | J10: 5 | K10: =IF(J10>1,J10/100,J10) -> 0.05 | L10: Unpaid | M10: =IF(L10="paid",H10*I10*(1-K10),0) -> 0 | N10: =IF(L10="paid",H10*I10,0) -> 0 | O10: =TEXT(B10,"mmm-yyy") -> Feb-2025
A11: O010 | B11: 45695 | C11: Anita Joseph | D11: South | E11: Anita Joseph | F11: =PROPER(E11) -> Anita Joseph | G11: Office Chair | H11: 2 | I11: 7500 | J11: 8 | K11: =IF(J11>1,J11/100,J11) -> 0.08 | L11: Paid | M11: =IF(L11="paid",H11*I11*(1-K11),0) -> 13800 | N11: =IF(L11="paid",H11*I11,0) -> 15000 | O11: =TEXT(B11,"mmm-yyy") -> Feb-2025
A12: O011 | B12: 45750 | C12: Kamal | D12: North | E12: Neha Sharma | F12: =PROPER(E12) -> Neha Sharma | G12: Desk | H12: 1 | I12: 9500 | J12: 3 | K12: =IF(J12>1,J12/100,J12) -> 0.03 | L12: Paid | M12: =IF(L12="paid",H12*I12*(1-K12),0) -> 9215 | N12: =IF(L12="paid",H12*I12,0) -> 9500 | O12: =TEXT(B12,"mmm-yyy") -> Apr-2025
A13: O012 | B13: 45705 | C13: Sunil | D13: West | E13: Rahul Nair | F13: =PROPER(E13) -> Rahul Nair | G13: Printer | H13: 1 | I13: 12000 | J13: 4 | K13: =IF(J13>1,J13/100,J13) -> 0.04 | L13: Paid | M13: =IF(L13="paid",H13*I13*(1-K13),0) -> 11520 | N13: =IF(L13="paid",H13*I13,0) -> 12000 | O13: =TEXT(B13,"mmm-yyy") -> Feb-2025
A14: O013 | B14: 45718 | C14: Aditya | D14: East | E14: Neha Sharma | F14: =PROPER(E14) -> Neha Sharma | G14: Mobile | H14: 6 | I14: 18000 | J14: 8 | K14: =IF(J14>1,J14/100,J14) -> 0.08 | L14: Paid | M14: =IF(L14="paid",H14*I14*(1-K14),0) -> 99360 | N14: =IF(L14="paid",H14*I14,0) -> 108000 | O14: =TEXT(B14,"mmm-yyy") -> Mar-2025
A15: O014 | B15: 45760 | C15: Priya | D15: West | E15: Neha Sharma | F15: =PROPER(E15) -> Neha Sharma | G15: Mobile | H15: 5 | I15: 18000 | J15: 0 | K15: =IF(J15>1,J15/100,J15) -> 0 | L15: Paid | M15: =IF(L15="paid",H15*I15*(1-K15),0) -> 90000 | N15: =IF(L15="paid",H15*I15,0) -> 90000 | O15: =TEXT(B15,"mmm-yyy") -> Apr-2025
A16: O015 | B16: 45724 | C16: Suresh | D16: South | E16: RAHUL NAIR | F16: =PROPER(E16) -> Rahul Nair | G16: Laptop | H16: 1 | I16: 55000 | J16: 7 | K16: =IF(J16>1,J16/100,J16) -> 0.07 | L16: Paid | M16: =IF(L16="paid",H16*I16*(1-K16),0) -> 51150 | N16: =IF(L16="paid",H16*I16,0) -> 55000 | O16: =TEXT(B16,"mmm-yyy") -> Mar-2025
A17: O016 | B17: 45709 | C17: Ritu | D17: North | E17: RIYA GUPTA | F17: =PROPER(E17) -> Riya Gupta | G17: Office Chair | H17: 3 | I17: 7500 | J17: 5 | K17: =IF(J17>1,J17/100,J17) -> 0.05 | L17: Paid | M17: =IF(L17="paid",H17*I17*(1-K17),0) -> 21375 | N17: =IF(L17="paid",H17*I17,0) -> 22500 | O17: =TEXT(B17,"mmm-yyy") -> Feb-2025
A18: O017 | B18: 45745 | C18: Kishore | D18: East | E18: srikanth verma | F18: =PROPER(E18) -> Srikanth Verma | G18: Desk | H18: 2 | I18: 9500 | J18: 6 | K18: =IF(J18>1,J18/100,J18) -> 0.06 | L18: Paid | M18: =IF(L18="paid",H18*I18*(1-K18),0) -> 17860 | N18: =IF(L18="paid",H18*I18,0) -> 19000 | O18: =TEXT(B18,"mmm-yyy") -> Mar-2025
A19: O018 | B19: 45749 | C19: Arun Kumar | D19: West | E19: Neha Sharma | F19: =PROPER(E19) -> Neha Sharma | G19: Laptop | H19: 7 | I19: 55000 | J19: 1 | K19: =IF(J19>1,J19/100,J19) -> 1 | L19: Unpaid | M19: =IF(L19="paid",H19*I19*(1-K19),0) -> 0 | N19: =IF(L19="paid",H19*I19,0) -> 0 | O19: =TEXT(B19,"mmm-yyy") -> Apr-2025
A20: O019 | B20: 45721 | C20: Tanvi | D20: South | E20: ANITA JOSEPH | F20: =PROPER(E20) -> Anita Joseph | G20: Printer | H20: 2 | I20: 12000 | J20: 5 | K20: =IF(J20>1,J20/100,J20) -> 0.05 | L20: Paid | M20: =IF(L20="paid",H20*I20*(1-K20),0) -> 22800 | N20: =IF(L20="paid",H20*I20,0) -> 24000 | O20: =TEXT(B20,"mmm-yyy") -> Mar-2025
A21: O020 | B21: 45759 | C21: Gita | D21: North | E21: Rahul Nair | F21: =PROPER(E21) -> Rahul Nair | G21: Mobile | H21: 4 | I21: 18000 | J21: 8 | K21: =IF(J21>1,J21/100,J21) -> 0.08 | L21: Paid | M21: =IF(L21="paid",H21*I21*(1-K21),0) -> 66240 | N21: =IF(L21="paid",H21*I21,0) -> 72000 | O21: =TEXT(B21,"mmm-yyy") -> Apr-2025
A22: O021 | B22: 45712 | C22: Neetu | D22: South | E22: Neha Sharma | F22: =PROPER(E22) -> Neha Sharma | G22: Desk | H22: 3 | I22: 9500 | J22: 6 | K22: =IF(J22>1,J22/100,J22) -> 0.06 | L22: Paid | M22: =IF(L22="paid",H22*I22*(1-K22),0) -> 26790 | N22: =IF(L22="paid",H22*I22,0) -> 28500 | O22: =TEXT(B22,"mmm-yyy") -> Feb-2025
... A69: O068 | B69: 45710 | C69: Kishore | D69: East | E69: RIYA GUPTA | F69: =PROPER(E69) -> Riya Gupta | G69: Desk | H69: 2 | I69: 9500 | J69: 6 | K69: =IF(J69>1,J69/100,J69) -> 0.06 | L69: Paid | M69: =IF(L69="paid",H69*I69*(1-K69),0) -> 17860 | N69: =IF(L69="paid",H69*I69,0) -> 19000 | O69: =TEXT(B69,"mmm-yyy") -> Feb-2025
A70: O069 | B70: 45719 | C70: Arjun Reddy | D70: South | E70: RAHUL NAIR | F70: =PROPER(E70) -> Rahul Nair | G70: Laptop | H70: 1 | I70: 55000 | J70: 6 | K70: =IF(J70>1,J70/100,J70) -> 0.06 | L70: Paid | M70: =IF(L70="paid",H70*I70*(1-K70),0) -> 51700 | N70: =IF(L70="paid",H70*I70,0) -> 55000 | O70: =TEXT(B70,"mmm-yyy") -> Mar-2025
A71: O070 | B71: 45754 | C71: Suman | D71: West | E71: Neha Sharma | F71: =PROPER(E71) -> Neha Sharma | G71: Printer | H71: 2 | I71: 12000 | J71: 3 | K71: =IF(J71>1,J71/100,J71) -> 0.03 | L71: Paid | M71: =IF(L71="paid",H71*I71*(1-K71),0) -> 23280 | N71: =IF(L71="paid",H71*I71,0) -> 24000 | O71: =TEXT(B71,"mmm-yyy") -> Apr-2025
A72: O071 | B72: 45704 | C72: Jagdish | D72: South | E72: ANITA JOSEPH | F72: =PROPER(E72) -> Anita Joseph | G72: Mobile | H72: 3 | I72: 18000 | J72: 5 | K72: =IF(J72>1,J72/100,J72) -> 0.05 | L72: Paid | M72: =IF(L72="paid",H72*I72*(1-K72),0) -> 51300 | N72: =IF(L72="paid",H72*I72,0) -> 54000 | O72: =TEXT(B72,"mmm-yyy") -> Feb-2025
A73: O072 | B73: 45746 | C73: Asha | D73: North | E73: Neha Sharma | F73: =PROPER(E73) -> Neha Sharma | G73: Desk | H73: 4 | I73: 9500 | J73: 7 | K73: =IF(J73>1,J73/100,J73) -> 0.07 | L73: Paid | M73: =IF(L73="paid",H73*I73*(1-K73),0) -> 35340 | N73: =IF(L73="paid",H73*I73,0) -> 38000 | O73: =TEXT(B73,"mmm-yyy") -> Mar-2025
A74: O073 | B74: 45758 | C74: Bhavesh | D74: East | E74: RAHUL NAIR | F74: =PROPER(E74) -> Rahul Nair | G74: Mobile | H74: 5 | I74: 18000 | J74: 6 | K74: =IF(J74>1,J74/100,J74) -> 0.06 | L74: Paid | M74: =IF(L74="paid",H74*I74*(1-K74),0) -> 84600 | N74: =IF(L74="paid",H74*I74,0) -> 90000 | O74: =TEXT(B74,"mmm-yyy") -> Apr-2025
A75: O074 | B75: 45721 | C75: Manju S | D75: West | E75: neha sharma | F75: =PROPER(E75) -> Neha Sharma | G75: Laptop | H75: 2 | I75: 55000 | J75: 5 | K75: =IF(J75>1,J75/100,J75) -> 0.05 | L75: Unpaid | M75: =IF(L75="paid",H75*I75*(1-K75),0) -> 0 | N75: =IF(L75="paid",H75*I75,0) -> 0 | O75: =TEXT(B75,"mmm-yyy") -> Mar-2025
A76: O075 | B76: 45714 | C76: Ritu | D76: South | E76: Srikanth Verma | F76: =PROPER(E76) -> Srikanth Verma | G76: Office Chair | H76: 1 | I76: 7500 | J76: 3 | K76: =IF(J76>1,J76/100,J76) -> 0.03 | L76: Paid | M76: =IF(L76="paid",H76*I76*(1-K76),0) -> 7275 | N76: =IF(L76="paid",H76*I76,0) -> 7500 | O76: =TEXT(B76,"mmm-yyy") -> Feb-2025
A77: O076 | B77: 45755 | C77: Kunal | D77: North | E77: RAHUL NAIR | F77: =PROPER(E77) -> Rahul Nair | G77: Printer | H77: 1 | I77: 12000 | J77: 4 | K77: =IF(J77>1,J77/100,J77) -> 0.04 | L77: Paid | M77: =IF(L77="paid",H77*I77*(1-K77),0) -> 11520 | N77: =IF(L77="paid",H77*I77,0) -> 12000 | O77: =TEXT(B77,"mmm-yyy") -> Apr-2025
A78: O077 | B78: 45730 | C78: Bhavana | D78: East | E78: NEHA SHARMA | F78: =PROPER(E78) -> Neha Sharma | G78: Mobile | H78: 2 | I78: 18000 | J78: 6 | K78: =IF(J78>1,J78/100,J78) -> 0.06 | L78: Paid | M78: =IF(L78="paid",H78*I78*(1-K78),0) -> 33840 | N78: =IF(L78="paid",H78*I78,0) -> 36000 | O78: =TEXT(B78,"mmm-yyy") -> Mar-2025
A79: O078 | B79: 19-Feb-2025 | C79: Shweta | D79: West | E79: Anita Joseph | F79: =PROPER(E79) -> Anita Joseph | G79: Desk | H79: 3 | I79: 9500 | J79: 6 | K79: =IF(J79>1,J79/100,J79) -> 0.06 | L79: Paid | M79: =IF(L79="paid",H79*I79*(1-K79),0) -> 26790 | N79: =IF(L79="paid",H79*I79,0) -> 28500 | O79: =TEXT(B79,"mmm-yyy") -> Feb-2025
A80: O079 | B80: 45748 | C80: Sahil | D80: South | E80: RAHUL NAIR | F80: =PROPER(E80) -> Rahul Nair | G80: Printer | H80: 4 | I80: 12000 | J80: 5 | K80: =IF(J80>1,J80/100,J80) -> 0.05 | L80: Paid | M80: =IF(L80="paid",H80*I80*(1-K80),0) -> 45600 | N80: =IF(L80="paid",H80*I80,0) -> 48000 | O80: =TEXT(B80,"mmm-yyy") -> Apr-2025
A81: O080 | B81: 45740 | C81: Aditi | D81: North | E81: Neha Sharma | F81: =PROPER(E81) -> Neha Sharma | G81: Laptop | H81: 1 | I81: 55000 | J81: 6 | K81: =IF(J81>1,J81/100,J81) -> 0.06 | L81: Paid | M81: =IF(L81="paid",H81*I81*(1-K81),0) -> 51700 | N81: =IF(L81="paid",H81*I81,0) -> 55000 | O81: =TEXT(B81,"mmm-yyy") -> Mar-2025
A82: O082 | B82: 45768 | C82: Arjun Reddy | D82: South | E82: neha sharma | F82: =PROPER(E82) -> Neha Sharma | G82: Laptop | H82: 2 | I82: 55000 | J82: 6 | K82: =IF(J82>1,J82/100,J82) -> 0.06 | L82: Paid | M82: =IF(L82="paid",H82*I82*(1-K82),0) -> 103400 | N82: =IF(L82="paid",H82*I82,0) -> 110000 | O82: =TEXT(B82,"mmm-yyy") -> Apr-2025
A83: O083 | B83: 45722 | C83: Pooja | D83: West | E83: RAHUL NAIR | F83: =PROPER(E83) -> Rahul Nair | G83: Desk | H83: 1 | I83: 9500 | J83: 3 | K83: =IF(J83>1,J83/100,J83) -> 0.03 | L83: Paid | M83: =IF(L83="paid",H83*I83*(1-K83),0) -> 9215 | N83: =IF(L83="paid",H83*I83,0) -> 9500 | O83: =TEXT(B83,"mmm-yyy") -> Mar-2025
A84: O084 | B84: 45733 | C84: Shiv | D84: North | E84: Neha Sharma | F84: =PROPER(E84) -> Neha Sharma | G84: Printer | H84: 2 | I84: 12000 | J84: 5 | K84: =IF(J84>1,J84/100,J84) -> 0.05 | L84: Paid | M84: =IF(L84="paid",H84*I84*(1-K84),0) -> 22800 | N84: =IF(L84="paid",H84*I84,0) -> 24000 | O84: =TEXT(B84,"mmm-yyy") -> Mar-2025
A85: O085 | B85: 45700 | C85: Ananya | D85: East | E85: RAHUL NAIR | F85: =PROPER(E85) -> Rahul Nair | G85: Mobile | H85: 3 | I85: 18000 | J85: 4 | K85: =IF(J85>1,J85/100,J85) -> 0.04 | L85: Paid | M85: =IF(L85="paid",H85*I85*(1-K85),0) -> 51840 | N85: =IF(L85="paid",H85*I85,0) -> 54000 | O85: =TEXT(B85,"mmm-yyy") -> Feb-2025
A86: O086 | B86: 45716 | C86: Ramesh | D86: South | E86: Anita Joseph | F86: =PROPER(E86) -> Anita Joseph | G86: Office Chair | H86: 2 | I86: 7500 | J86: 4 | K86: =IF(J86>1,J86/100,J86) -> 0.04 | L86: Paid | M86: =IF(L86="paid",H86*I86*(1-K86),0) -> 14400 | N86: =IF(L86="paid",H86*I86,0) -> 15000 | O86: =TEXT(B86,"mmm-yyy") -> Feb-2025
A87: O087 | B87: 45751 | C87: Pranav | D87: West | E87: neha sharma | F87: =PROPER(E87) -> Neha Sharma | G87: Laptop | H87: 3 | I87: 55000 | J87: 5 | K87: =IF(J87>1,J87/100,J87) -> 0.05 | L87: Paid | M87: =IF(L87="paid",H87*I87*(1-K87),0) -> 156750 | N87: =IF(L87="paid",H87*I87,0) -> 165000 | O87: =TEXT(B87,"mmm-yyy") -> Apr-2025
A88: O088 | B88: 45725 | C88: Deepak | D88: East | E88: RAHUL NAIR | F88: =PROPER(E88) -> Rahul Nair | G88: Printer | H88: 2 | I88: 12000 | J88: 6 | K88: =IF(J88>1,J88/100,J88) -> 0.06 | L88: Paid | M88: =IF(L88="paid",H88*I88*(1-K88),0) -> 22560 | N88: =IF(L88="paid",H88*I88,0) -> 24000 | O88: =TEXT(B88,"mmm-yyy") -> Mar-2025
A89: O089 | B89: 45747 | C89: Suman | D89: North | E89: ANITA JOSEPH | F89: =PROPER(E89) -> Anita Joseph | G89: Mobile | H89: 4 | I89: 18000 | J89: 8 | K89: =IF(J89>1,J89/100,J89) -> 0.08 | L89: Paid | M89: =IF(L89="paid",H89*I89*(1-K89),0) -> 66240 | N89: =IF(L89="paid",H89*I89,0) -> 72000 | O89: =TEXT(B89,"mmm-yyy") -> Mar-2025
A90: O090 | B90: 45711 | C90: Ragini | D90: South | E90: Neha Sharma | F90: =PROPER(E90) -> Neha Sharma | G90: Desk | H90: 2 | I90: 9500 | J90: 5 | K90: =IF(J90>1,J90/100,J90) -> 0.05 | L90: Paid | M90: =IF(L90="paid",H90*I90*(1-K90),0) -> 18050 | N90: =IF(L90="paid",H90*I90,0) -> 19000 | O90: =TEXT(B90,"mmm-yyy") -> Feb-2025
A91: O091 | B91: 45749 | C91: Nikita | D91: West | E91: RAHUL NAIR | F91: =PROPER(E91) -> Rahul Nair | G91: Printer | H91: 3 | I91: 12000 | J91: 5 | K91: =IF(J91>1,J91/100,J91) -> 0.05 | L91: Paid | M91: =IF(L91="paid",H91*I91*(1-K91),0) -> 34200 | N91: =IF(L91="paid",H91*I91,0) -> 36000 | O91: =TEXT(B91,"mmm-yyy") -> Apr-2025
A92: O092 | B92: 45752 | C92: Asha | D92: East | E92: neha sharma | F92: =PROPER(E92) -> Neha Sharma | G92: Mobile | H92: 4 | I92: =SUBSTITUTE(I99,"₹","") -> 18000 | J92: 6 | K92: =IF(J92>1,J92/100,J92) -> 0.06 | L92: Pending | M92: =IF(L92="paid",H92*I92*(1-K92),0) -> 0 | N92: =IF(L92="paid",H92*I92,0) -> 0 | O92: =TEXT(B92,"mmm-yyy") -> Apr-2025
A93: O093 | B93: 45776 | C93: Sunaina | D93: East | E93: RIYA GUPTA | F93: =PROPER(E93) -> Riya Gupta | G93: Office Chair | H93: 2 | I93: 7500 | J93: 5 | K93: =IF(J93>1,J93/100,J93) -> 0.05 | L93: Paid | M93: =IF(L93="paid",H93*I93*(1-K93),0) -> 14250 | N93: =IF(L93="paid",H93*I93,0) -> 15000 | O93: =TEXT(B93,"mmm-yyy") -> Apr-2025
A94: O094 | B94: 45727 | C94: Santhosh | D94: East | E94: neha sharma | F94: =PROPER(E94) -> Neha Sharma | G94: Mobile | H94: 2 | I94: 18000 | J94: 3 | K94: =IF(J94>1,J94/100,J94) -> 0.03 | L94: Paid | M94: =IF(L94="paid",H94*I94*(1-K94),0) -> 34920 | N94: =IF(L94="paid",H94*I94,0) -> 36000 | O94: =TEXT(B94,"mmm-yyy") -> Mar-2025
A95: O095 | B95: 45695 | C95: Sahil | D95: North | E95: RAHUL NAIR | F95: =PROPER(E95) -> Rahul Nair | G95: Laptop | H95: 4 | I95: 55000 | J95: 7 | K95: =IF(J95>1,J95/100,J95) -> 0.07 | L95: Paid | M95: =IF(L95="paid",H95*I95*(1-K95),0) -> 204600 | N95: =IF(L95="paid",H95*I95,0) -> 220000 | O95: =TEXT(B95,"mmm-yyy") -> Feb-2025
A96: O096 | B96: 45767 | C96: Meena | D96: West | E96: Neha Sharma | F96: =PROPER(E96) -> Neha Sharma | G96: Office Chair | H96: 3 | I96: 7500 | J96: 6 | K96: =IF(J96>1,J96/100,J96) -> 0.06 | L96: Pending | M96: =IF(L96="paid",H96*I96*(1-K96),0) -> 0 | N96: =IF(L96="paid",H96*I96,0) -> 0 | O96: =TEXT(B96,"mmm-yyy") -> Apr-2025
A97: O097 | B97: 45741 | C97: Ashok | D97: South | E97: ANITA JOSEPH | F97: =PROPER(E97) -> Anita Joseph | G97: Printer | H97: 2 | I97: 12000 | J97: 5 | K97: =IF(J97>1,J97/100,J97) -> 0.05 | L97: Paid | M97: =IF(L97="paid",H97*I97*(1-K97),0) -> 22800 | N97: =IF(L97="paid",H97*I97,0) -> 24000 | O97: =TEXT(B97,"mmm-yyy") -> Mar-2025
A98: O098 | B98: 45763 | C98: Arun Kumar | D98: West | E98: Neha Sharma | F98: =PROPER(E98) -> Neha Sharma | G98: Laptop | H98: 7 | I98: 55000 | J98: 1 | K98: =IF(J98>1,J98/100,J98) -> 1 | L98: Paid | M98: =IF(L98="paid",H98*I98*(1-K98),0) -> 0 | N98: =IF(L98="paid",H98*I98,0) -> 385000 | O98: =TEXT(B98,"mmm-yyy") -> Apr-2025
A99: O099 | B99: 45693 | C99: Bhavya | D99: East | E99: RAHUL NAIR | F99: =PROPER(E99) -> Rahul Nair | G99: Mobile | H99: 2 | I99: 18000 | J99: 5 | K99: =IF(J99>1,J99/100,J99) -> 0.05 | L99: Paid | M99: =IF(L99="paid",H99*I99*(1-K99),0) -> 34200 | N99: =IF(L99="paid",H99*I99,0) -> 36000 | O99: =TEXT(B99,"mmm-yyy") -> Feb-2025
A100: O100 | B100: 45731 | C100: Vinod | D100: South | E100: Neha Sharma | F100: =PROPER(E100) -> Neha Sharma | G100: Desk | H100: 1 | I100: 9500 | J100: 3 | K100: =IF(J100>1,J100/100,J100) -> 0.03 | L100: Paid | M100: =IF(L100="paid",H100*I100*(1-K100),0) -> 9215 | N100: =IF(L100="paid",H100*I100,0) -> 9500 | O100: =TEXT(B100,"mmm-yyy") -> Mar-2025
A101: O101 | B101: 45715 | C101: Ankit | D101: West | E101: RAHUL NAIR | F101: =PROPER(E101) -> Rahul Nair | G101: Printer | H101: 2 | I101: 12000 | J101: 6 | K101: =IF(J101>1,J101/100,J101) -> 0.06 | L101: Paid | M101: =IF(L101="paid",H101*I101*(1-K101),0) -> 22560 | N101: =IF(L101="paid",H101*I101,0) -> 24000 | O101: =TEXT(B101,"mmm-yyy") -> Feb-2025
A102: O102 | B102: 45755 | C102: Sahil | D102: South | E102: Neha Sharma | F102: =PROPER(E102) -> Neha Sharma | G102: Mobile | H102: 3 | I102: 18000 | J102: 5 | K102: =IF(J102>1,J102/100,J102) -> 0.05 | L102: Paid | M102: =IF(L102="paid",H102*I102*(1-K102),0) -> 51300 | N102: =IF(L102="paid",H102*I102,0) -> 54000 | O102: =TEXT(B102,"mmm-yyy") -> Apr-2025
A103: O103 | B103: 45710 | C103: Shalini S | D103: East | E103: ANITA JOSEPH | F103: =PROPER(E103) -> Anita Joseph | G103: Desk | H103: 4 | I103: 9500 | J103: 6 | K103: =IF(J103>1,J103/100,J103) -> 0.06 | L103: Paid | M103: =IF(L103="paid",H103*I103*(1-K103),0) -> 35720 | N103: =IF(L103="paid",H103*I103,0) -> 38000 | O103: =TEXT(B103,"mmm-yyy") -> Feb-2025
A104: O104 | B104: 45661 | C104: Priya | D104: West | E104: Neha Sharma | F104: =PROPER(E104) -> Neha Sharma | G104: Printer | H104: 3 | I104: 12000 | J104: 5 | K104: =IF(J104>1,J104/100,J104) -> 0.05 | L104: Paid | M104: =IF(L104="paid",H104*I104*(1-K104),0) -> 34200 | N104: =IF(L104="paid",H104*I104,0) -> 36000 | O104: =TEXT(B104,"mmm-yyy") -> Jan-2025
... A116: O116 | B116: 45703 | C116: Maya | D116: South | E116: RAHUL NAIR | F116: =PROPER(E116) -> Rahul Nair | G116: Printer | H116: 3 | I116: 12000 | J116: 4 | K116: =IF(J116>1,J116/100,J116) -> 0.04 | L116: Paid | M116: =IF(L116="paid",H116*I116*(1-K116),0) -> 34560 | N116: =IF(L116="paid",H116*I116,0) -> 36000 | O116: =TEXT(B116,"mmm-yyy") -> Feb-2025
A117: O117 | B117: 21-Apr-2025 | C117: Neha Sharma | D117: West | E117: ANITA JOSEPH | F117: =PROPER(E117) -> Anita Joseph | G117: Desk | H117: 2 | I117: 9500 | J117: 5 | K117: =IF(J117>1,J117/100,J117) -> 0.05 | L117: Paid | M117: =IF(L117="paid",H117*I117*(1-K117),0) -> 18050 | N117: =IF(L117="paid",H117*I117,0) -> 19000 | O117: =TEXT(B117,"mmm-yyy") -> Apr-2025
A118: O118 | B118: 45718 | C118: Dinesh | D118: North | E118: Neha Sharma | F118: =PROPER(E118) -> Neha Sharma | G118: Office Chair | H118: 1 | I118: 7500 | J118: 6 | K118: =IF(J118>1,J118/100,J118) -> 0.06 | L118: Paid | M118: =IF(L118="paid",H118*I118*(1-K118),0) -> 7050 | N118: =IF(L118="paid",H118*I118,0) -> 7500 | O118: =TEXT(B118,"mmm-yyy") -> Mar-2025
A119: O119 | B119: 45754 | C119: Suresh | D119: East | E119: RAHUL NAIR | F119: =PROPER(E119) -> Rahul Nair | G119: Mobile | H119: 5 | I119: 18000 | J119: 7 | K119: =IF(J119>1,J119/100,J119) -> 0.07 | L119: Pending | M119: =IF(L119="paid",H119*I119*(1-K119),0) -> 0 | N119: =IF(L119="paid",H119*I119,0) -> 0 | O119: =TEXT(B119,"mmm-yyy") -> Apr-2025
A120: O120 | B120: 45704 | C120: Ramesh | D120: South | E120: Neha Sharma | F120: =PROPER(E120) -> Neha Sharma | G120: Printer | H120: 3 | I120: 12000 | J120: 6 | K120: =IF(J120>1,J120/100,J120) -> 0.06 | L120: Paid | M120: =IF(L120="paid",H120*I120*(1-K120),0) -> 33840 | N120: =IF(L120="paid",H120*I120,0) -> 36000 | O120: =TEXT(B120,"mmm-yyy") -> Feb-2025
A121: O121 | B121: 45727 | C121: Aditi | D121: West | E121: RAHUL NAIR | F121: =PROPER(E121) -> Rahul Nair | G121: Laptop | H121: 1 | I121: 55000 | J121: 5 | K121: =IF(J121>1,J121/100,J121) -> 0.05 | L121: Paid | M121: =IF(L121="paid",H121*I121*(1-K121),0) -> 52250 | N121: =IF(L121="paid",H121*I121,0) -> 55000 | O121: =TEXT(B121,"mmm-yyy") -> Mar-2025
A122: O122 | B122: 22-Feb-2025 | C122: NoteDate | D122: South | E122: Neha Sharma | F122: =PROPER(E122) -> Neha Sharma | G122: Mobile | H122: 2 | I122: 18000 | J122: 4 | K122: =IF(J122>1,J122/100,J122) -> 0.04 | L122: Paid | M122: =IF(L122="paid",H122*I122*(1-K122),0) -> 34560 | N122: =IF(L122="paid",H122*I122,0) -> 36000 | O122: =TEXT(B122,"mmm-yyy") -> Feb-2025
A123: O123 | B123: 45749 | C123: Pranav | D123: North | E123: Anita Joseph | F123: =PROPER(E123) -> Anita Joseph | G123: Desk | H123: 3 | I123: 9500 | J123: 6 | K123: =IF(J123>1,J123/100,J123) -> 0.06 | L123: Paid | M123: =IF(L123="paid",H123*I123*(1-K123),0) -> 26790 | N123: =IF(L123="paid",H123*I123,0) -> 28500 | O123: =TEXT(B123,"mmm-yyy") -> Apr-2025
A124: O124 | B124: 45724 | C124: Gita | D124: West | E124: RAHUL NAIR | F124: =PROPER(E124) -> Rahul Nair | G124: Printer | H124: 2 | I124: 12000 | J124: 5 | K124: =IF(J124>1,J124/100,J124) -> 0.05 | L124: Paid | M124: =IF(L124="paid",H124*I124*(1-K124),0) -> 22800 | N124: =IF(L124="paid",H124*I124,0) -> 24000 | O124: =TEXT(B124,"mmm-yyy") -> Mar-2025
A125: O125 | B125: 45705 | C125: Sahil | D125: East | E125: Neha Sharma | F125: =PROPER(E125) -> Neha Sharma | G125: Mobile | H125: 6 | I125: 18000 | J125: 8 | K125: =IF(J125>1,J125/100,J125) -> 0.08 | L125: Paid | M125: =IF(L125="paid",H125*I125*(1-K125),0) -> 99360 | N125: =IF(L125="paid",H125*I125,0) -> 108000 | O125: =TEXT(B125,"mmm-yyy") -> Feb-2025

Sheet Questions
A1: Questions | B1: Answers
A2: List 3 issues (anomalies) you found in the dataset and explain how it affects the analysis | B2: 1. Discount % column has mixed Format :-numeric Value,Percentage(8%),Unit price has enteries like 18000,₹18000(order no.0115), 2.Missing and Inconsistent Data(salesperson name missing,and salesperson name inconsistent Capitalization), 3.Duplicate and repeated order ID's(0080,0100).
A3: Fill the “Net Revenue” and “Revenue” columns in the Orders sheet using formulas. For orders where Payment Status = Paid: - Net Revenue = Quantity × Unit Price × (1 − Discount%) - Revenue = Quantity × Unit Price | B3: Which is mentioned in Order Tables Calculations.
A4: Create a pivot table showing Net Revenue for each Region. Mention the Region with highest Net Revenue | B4: West Region Has Highest Net Revenue .(1477815)
A5: Calculate the Total Revenue (Answer using formula) | B5: =SUM(orders!N2:N125) -> 5886000
A6: What percentage of total orders are Unpaid or Pending? (Answer using formula) | B6: =(COUNTIF(orders!L2:L125,"Unpaid") + COUNTIF(orders!L2:L125,"Pending")) / COUNTA(orders!L2:L125) * 100 -> 14.516129
A7: 1. Fill the “Month” column in the Orders subsheet by extracting the month from the Order Date using a formula. 2. Insert a new subsheet with name "Products sold" & build a summary table that shows the total quantity sold for each product, month-wise. (Answer using formula, Rearrange columns if required) 3. Mention which month and which product recorded the highest total quantity sold based on the summary. | B7: The product Mobile recorded the highest total quantity sold (145 units) across all months. The highest quantity in a single month was also for Mobile in March 2025, with 58 units sold.
A8: Determine whether higher discounts lead to higher revenue? Explain your conclusion using supporting numbers or statistics from the data. | B8: Discount 0–5%:- Total Net Revenue gradually increases with discount up to 5%. Example: At 5% discount, the Grand Total Net Revenue is 1,436,875, which is the highest in the dataset.
B9: Discount 6–8%:- Total Net Revenue slightly decreases at 6–8% discounts (1,355,480 at 6% and 1,016,490 at 7%, 676,200 at 8%). This shows that higher discounts do not always result in higher revenue.
B10: Product impact:- Laptops and Mobiles generate the highest revenue regardless of discount %, because these are high-value items.
B11: Products with lower unit prices (Desks, Office Chairs, Printers) contribute much less to total revenue even at higher discounts.
B13: Conclusion:-
B14: Giving higher discounts does not automatically lead to higher revenue.
B15: The highest revenue comes from moderate discounts around 5%, especially on high-value products like Laptops and Mobiles.
B16: Very high discounts (6–8%) actually reduce total revenue, because these discounts may be on lower-priced products or smaller sales volumes.
B17: Revenue depends more on product price and quantity sold, with discount being a secondary factor.

Sheet Net Revenue by Region
A1: Net Revenue By Region
A3: Payment Status | B3: Paid
A5: Region | B5: SUM of Net Revenue
A6: East | B6: 1089985
A7: North | B7: 1300460
A8: South | B8: 1312220
A9: West | B9: 1477815
A10: Grand Total | B10: 5180480

Sheet Product Sold
A1: Summary Table
A3: Product | B3: 45658 | C3: 45689 | D3: 45717 | E3: 45748 | F3: Total of Product wise
A4: {=_xlfn.UNIQUE(orders!G2:G125)} -> Printer | B4: =SUMIFS(orders!$H$2:$H$125, orders!$G$2:$G$125, $A4, orders!$O$2:$O$125, B$3) -> 3 | C4: =SUMIFS(orders!$H$2:$H$125, orders!$G$2:$G$125, $A4, orders!$O$2:$O$125, C$3) -> 17 | D4: =SUMIFS(orders!$H$2:$H$125, orders!$G$2:$G$125, $A4, orders!$O$2:$O$125, D$3) -> 16 | E4: =SUMIFS(orders!$H$2:$H$125, orders!$G$2:$G$125, $A4, orders!$O$2:$O$125, E$3) -> 30 | F4: =SUM(B4:E4) -> 66
A5: Office Chair | B5: =SUMIFS(orders!$H$2:$H$125, orders!$G$2:$G$125, $A5, orders!$O$2:$O$125, B$3) -> 0 | C5: =SUMIFS(orders!$H$2:$H$125, orders!$G$2:$G$125, $A5, orders!$O$2:$O$125, C$3) -> 10 | D5: =SUMIFS(orders!$H$2:$H$125, orders!$G$2:$G$125, $A5, orders!$O$2:$O$125, D$3) -> 17 | E5: =SUMIFS(orders!$H$2:$H$125, orders!$G$2:$G$125, $A5, orders!$O$2:$O$125, E$3) -> 9 | F5: =SUM(B5:E5) -> 36
A6: Mobile | B6: =SUMIFS(orders!$H$2:$H$125, orders!$G$2:$G$125, $A6, orders!$O$2:$O$125, B$3) -> 0 | C6: =SUMIFS(orders!$H$2:$H$125, orders!$G$2:$G$125, $A6, orders!$O$2:$O$125, C$3) -> 39 | D6: =SUMIFS(orders!$H$2:$H$125, orders!$G$2:$G$125, $A6, orders!$O$2:$O$125, D$3) -> 58 | E6: =SUMIFS(orders!$H$2:$H$125, orders!$G$2:$G$125, $A6, orders!$O$2:$O$125, E$3) -> 48 | F6: =SUM(B6:E6) -> 145
A7: Laptop | B7: =SUMIFS(orders!$H$2:$H$125, orders!$G$2:$G$125, $A7, orders!$O$2:$O$125, B$3) -> 0 | C7: =SUMIFS(orders!$H$2:$H$125, orders!$G$2:$G$125, $A7, orders!$O$2:$O$125, C$3) -> 24 | D7: =SUMIFS(orders!$H$2:$H$125, orders!$G$2:$G$125, $A7, orders!$O$2:$O$125, D$3) -> 16 | E7: =SUMIFS(orders!$H$2:$H$125, orders!$G$2:$G$125, $A7, orders!$O$2:$O$125, E$3) -> 20 | F7: =SUM(B7:E7) -> 60
A8: Desk | B8: =SUMIFS(orders!$H$2:$H$125, orders!$G$2:$G$125, $A8, orders!$O$2:$O$125, B$3) -> 0 | C8: =SUMIFS(orders!$H$2:$H$125, orders!$G$2:$G$125, $A8, orders!$O$2:$O$125, C$3) -> 25 | D8: =SUMIFS(orders!$H$2:$H$125, orders!$G$2:$G$125, $A8, orders!$O$2:$O$125, D$3) -> 11 | E8: =SUMIFS(orders!$H$2:$H$125, orders!$G$2:$G$125, $A8, orders!$O$2:$O$125, E$3) -> 15 | F8: =SUM(B8:E8) -> 51
A9: Total of Month Wise | B9: =SUM(B4:B8) -> 3 | C9: =SUM(C4:C8) -> 115 | D9: =SUM(D4:D8) -> 118 | E9: =SUM(E4:E8) -> 122

Sheet Higher Discount
A1: SUM of Net Revenue | B1: Product
A2: Discount% | B2: Desk | C2: Laptop | D2: Mobile | E2: Office Chair | F2: Printer | G2: Grand Total
A3: 0 | D3: 90000 | G3: 90000
A4: 0.02 | B4: 0 | G4: 0
A5: 0.03 | B5: 36860 | D5: 122220 | E5: 7275 | F5: 34920 | G5: 201275
A6: 0.04 | B6: 45600 | D6: 241920 | E6: 36000 | F6: 80640 | G6: 404160
A7: 0.05 | B7: 36100 | C7: 470250 | D7: 427500 | E7: 35625 | F7: 467400 | G7: 1436875
A8: 0.06 | B8: 205390 | C8: 672100 | D8: 304560 | E8: 49350 | F8: 124080 | G8: 1355480
A9: 0.07 | B9: 35340 | C9: 869550 | D9: 66960 | F9: 44640 | G9: 1016490
A10: 0.08 | C10: 0 | D10: 662400 | E10: 13800 | G10: 676200
A11: 1 | C11: 0 | G11: 0
A12: Grand Total | B12: 359290 | C12: 2011900 | D12: 1915560 | E12: 142050 | F12: 751680 | G12: 5180480
